Metadata-Version: 2.1
Name: devtools-text-repeater
Version: 1.0.1
Summary: Text repeater
Home-page: https://devtools.at/tools/text-repeater
Author: DevTools.at
Author-email: hello@devtools.at
Project-URL: Homepage, https://devtools.at/tools/text-repeater
Project-URL: Repository, https://github.com/devtools-at/text-repeater
Classifier: Development Status :: 4 - Beta
Classifier: Intended Audience :: Developers
Classifier: License :: OSI Approved :: MIT License
Classifier: Programming Language :: Python :: 3
Requires-Python: >=3.8
